carmen/__init__.py
carmen/rotator.py
carmenproxy-0.1.0.dist-info/DESCRIPTION.rst
carmenproxy-0.1.0.dist-info/METADATA
carmenproxy-0.1.0.dist-info/RECORD
carmenproxy-0.1.0.dist-info/WHEEL
carmenproxy-0.1.0.dist-info/metadata.json
carmenproxy-0.1.0.dist-info/top_level.txt
tests/__init__.py
tests/test_rotator.py
