Metadata-Version: 2.0
Name: carmenproxy
Version: 0.1.0
Summary: Tool for proxying programmatic HTTP requests.
Home-page: https://github.com/mark-hoffmann/fastteradata
Author: Mark Hoffmann
Author-email: markkhoffmann@gmail.com
License: UNKNOWN
Platform: UNKNOWN
Classifier: Development Status :: 2 - Pre-Alpha
Classifier: Programming Language :: Python
Classifier: Programming Language :: Python :: 3
Classifier: Programming Language :: Python :: 3.6
Requires-Dist: beautifulsoup4
Requires-Dist: bs4
Requires-Dist: fake-useragent
Requires-Dist: pytest
